ptvpy/__init__.py
ptvpy/__main__.py
ptvpy/_cli_export.py
ptvpy/_cli_generate.py
ptvpy/_cli_process.py
ptvpy/_cli_profile.py
ptvpy/_cli_root.py
ptvpy/_cli_utils.py
ptvpy/_cli_view.py
ptvpy/_profile.py
ptvpy/_schema.py
ptvpy/_version.py
ptvpy/generate.py
ptvpy/io.py
ptvpy/plot.py
ptvpy/process.py
ptvpy/profile_template.toml
ptvpy/utils.py
ptvpy-0.10.2.dist-info/LICENSE.txt
ptvpy-0.10.2.dist-info/METADATA
ptvpy-0.10.2.dist-info/WHEEL
ptvpy-0.10.2.dist-info/entry_points.txt
ptvpy-0.10.2.dist-info/top_level.txt
ptvpy-0.10.2.dist-info/RECORD
